piesharkx/__init__.py
piesharkx/blueprint.py
piesharkx/cli.py
piesharkx/configuration.py
piesharkx/cookies.py
piesharkx/date_moduler.py
piesharkx/localcontex.py
piesharkx/logger.py
piesharkx/main.py
piesharkx/printer.py
piesharkx/pydejs.py
piesharkx/sessions.py
piesharkx/templates.py
piesharkx/handler/__init__.py
piesharkx/handler/endecryptions.py
piesharkx/handler/error_handler.py
piesharkx/handler/handshake.py
piesharkx/handler/obfuscator.py
piesharkx/handler/requests_ansyc.py
piesharkx/js/JSObus.js
piesharkx/js/__init__.py
piesharkx/middleware/__init__.py
piesharkx/middleware/headerGuard.py
piesharkx/middleware/limiter.py
piesharkx/middleware/memoryBrowser.py
piesharkx/middleware/mimet.py
piesharkx/middleware/requests.py
piesharkx-0.1.0.dist-info/LICENSE
piesharkx-0.1.0.dist-info/METADATA
piesharkx-0.1.0.dist-info/WHEEL
piesharkx-0.1.0.dist-info/entry_points.txt
piesharkx-0.1.0.dist-info/top_level.txt
piesharkx-0.1.0.dist-info/RECORD
