Metadata-Version: 2.2
Name: piesharkx
Version: 0.1.0
Summary: Mini Framework for Human
Home-page: https://github.com/LcfherShell/piesharkxs
Author: LcfherShell
Author-email: lcfhershell@tutanota.com
License: MIT
Project-URL: Bug Tracker, https://github.com/LcfherShell/piesharkx/issues
Project-URL: Documentation, https://github.com/LcfherShell/piesharkx#readme
Keywords: web,framework,pieshark
Classifier: Development Status :: 3 - Alpha
Classifier: Intended Audience :: Developers
Classifier: License :: OSI Approved :: MIT License
Classifier: Operating System :: OS Independent
Classifier: Programming Language :: Python :: 3.8
Classifier: Programming Language :: Python :: 3.9
Classifier: Programming Language :: Python :: 3.10
Classifier: Programming Language :: Python :: 3.11
Classifier: Programming Language :: Python :: 3.12
Requires-Python: >=3.8
License-File: LICENSE
Requires-Dist: webob>=1.8.7
Requires-Dist: parse>=1.19.0
Requires-Dist: colorama>=0.4.4
Requires-Dist: Werkzeug>=2.0.0
Requires-Dist: pycryptodome>=3.18.0
Requires-Dist: beautifulsoup4>=4.12.0
Requires-Dist: chardet>=5.1.0
Requires-Dist: requests-html
Provides-Extra: dev
Requires-Dist: pytest>=6.0; extra == "dev"
Requires-Dist: pytest-cov; extra == "dev"
Requires-Dist: black; extra == "dev"
Requires-Dist: flake8; extra == "dev"
Requires-Dist: mypy; extra == "dev"
Dynamic: author
Dynamic: author-email
Dynamic: classifier
Dynamic: description
Dynamic: description-content-type
Dynamic: home-page
Dynamic: keywords
Dynamic: license
Dynamic: project-url
Dynamic: provides-extra
Dynamic: requires-dist
Dynamic: requires-python
Dynamic: summary
